Workbook
Name TC: Parametros!$B$4
Name ANIO: Parametros!$B$5
Name FondoObj: Parametros!$B$6
Name SaldoHoy: Parametros!$B$7
Name MESCALC: Parametros!$B$8
Name Monedas: Parametros!$D$12:$D$13
Name Tipos: Parametros!$E$12:$E$13
Name Miembros: Parametros!$F$12:$F$15
Name Medios: Parametros!$G$12:$G$17
Name EstadosCobro: Parametros!$H$12:$H$15
Name CatEgreso: Parametros!$I$12:$I$26
Name CatIngreso: Parametros!$J$12:$J$17
Name Frecuencias: Parametros!$L$12:$L$16
Name TablaFrec: Parametros!$L$12:$M$16
Name ClaveIPC: 'Inflacion INDEC'!$A$5:$A$64
Name IndiceIPC: 'Inflacion INDEC'!$C$5:$C$64

Sheet Portada
B2: FINANZAS DE LA FAMILIA
B3: Plan económico doméstico · Año 2026
B5: ¿Cómo está organizado este libro?
B6: Parámetros | C6: Empezá acá: tipo de cambio, mes de cálculo y tabla de frecuencias.
B7: Inflacion INDEC | C7: Cargá el índice IPC cada mes. Reajusta todos los alquileres.
B8: Guia INDEC | C8: Paso a paso para traer el IPC automático con Power Query.
B9: Inquilinos | C9: Los 29 inquilinos. El alquiler se reajusta solo por inflación INDEC.
B10: Cobros | C10: Detalle de cada cobro de alquiler (una fila por pago).
B11: Tablero Inquilinos | C11: Tablero automático: quién pagó cada mes y % de cumplimiento.
B12: Movimientos | C12: Ingresos y egresos de la familia (Yo, Hermana, Mamá).
B13: Resumen Mensual | C13: Resumen automático mes a mes: ingresos, egresos y ahorro.
B14: Presupuesto | C14: Presupuesto por categoría vs gasto real del año.
B15: Indicadores | C15: Indicadores financieros para tomar mejores decisiones.
B17: Código de colores
B18: Azul | C18: Dato que cargás vos (editable)
B19: Negro | C19: Cálculo / fórmula (no tocar)
B20: Verde | C20: Trae datos de otra hoja
B21: Fondo amarillo | C21: Supuesto clave a revisar
B23: Reajuste de alquileres: | C23: Cada inquilino tiene un 'mes base' y una frecuencia. El alquiler sube según el IPC del INDEC que cargás en la hoja 'Inflacion INDEC'.

Sheet Parametros
A1: PARÁMETROS Y SUPUESTOS
A2: Actualizá el tipo de cambio y el mes de cálculo. Las listas alimentan los menús desplegables.
A4: Tipo de cambio USD → ARS | B4: 1150
A5: Año de trabajo | B5: 2026
A6: Fondo de emergencia objetivo (meses) | B6: 6
A7: Saldo disponible hoy (ARS) | B7: 0
A8: Mes de cálculo del reajuste | B8: 46143
D11: Monedas | E11: Tipo mov. | F11: Miembros | G11: Medios de pago | H11: Estado cobro | I11: Categorías egreso | J11: Categorías ingreso | L11: Frecuencia | M11: Meses
D12: ARS | E12: Ingreso | F12: Yo | G12: Efectivo | H12: Cobrado | I12: Vivienda/Expensas | J12: Alquileres | L12: Mensual | M12: 1
D13: USD | E13: Egreso | F13: Hermana | G13: Transferencia | H13: Pendiente | I13: Servicios (luz/gas/agua) | J13: Sueldo | L13: Trimestral | M13: 3
F14: Mamá | G14: Cheque | H14: Parcial | I14: Internet/Teléfono | J14: Honorarios | L14: Semestral | M14: 6
F15: Familia | G15: Débito | H15: Vencido | I15: Supermercado/Comida | J15: Intereses/Inversiones | L15: Anual | M15: 12
G16: Mercado Pago | I16: Salud/Obra social | J16: Venta de activos | L16: Sin ajuste | M16: 0
G17: Otro | I17: Transporte/Auto | J17: Otros ingresos
I18: Educación
I19: Impuestos (ABL/AFIP/Rentas)
I20: Mantenimiento locales
I21: Seguros
I22: Honorarios/Gestión
I23: Ocio/Viajes
I24: Indumentaria
I25: Ahorro/Inversión
I26: Otros

Sheet Inquilinos
A1: LISTADO DE INQUILINOS
A2: IPC ajuste: coeficiente manual (1.0 = sin ajuste; 1.45 = +45%). Alquiler ajustado se calcula solo.
A4: ID | B4: Inquilino | C4: Local / Propiedad | D4: Inicio contrato | E4: Fin contrato | F4: Mes base (ajuste) | G4: Alquiler base | H4: Moneda | I4: Frecuencia ajuste | J4: IPC ajuste (coef.) | K4: Alquiler ajustado | L4: Alquiler ajustado (ARS) | M4: Día venc. | N4: Estado | O4: Notas
A5: 1 | B5: Inquilino 01 | C5: Local 01 | D5: 45292 | F5: 45658 | G5: 631 | H5: USD | I5: Trimestral | J5: 1 | K5: =IF(G5="","",G5*J5) -> 631 | L5: =IF(K5="","",IF(H5="USD",K5*TC,K5)) | M5: 5 | N5: Activo
A6: 2 | B6: Inquilino 02 | C6: Local 02 | D6: 45323 | F6: 45689 | G6: 382000 | H6: ARS | I6: Trimestral | J6: 1 | K6: =IF(G6="","",G6*J6) -> 382000 | L6: =IF(K6="","",IF(H6="USD",K6*TC,K6)) | M6: 1 | N6: Activo
A7: 3 | B7: Inquilino 03 | C7: Local 03 | D7: 45352 | F7: 45717 | G7: 204000 | H7: ARS | I7: Trimestral | J7: 1 | K7: =IF(G7="","",G7*J7) -> 204000 | L7: =IF(K7="","",IF(H7="USD",K7*TC,K7)) | M7: 5 | N7: Activo
A8: 4 | B8: Inquilino 04 | C8: Local 04 | D8: 45383 | F8: 45748 | G8: 600000 | H8: ARS | I8: Trimestral | J8: 1 | K8: =IF(G8="","",G8*J8) -> 600000 | L8: =IF(K8="","",IF(H8="USD",K8*TC,K8)) | M8: 1 | N8: Activo
A9: 5 | B9: Inquilino 05 | C9: Local 05 | D9: 45413 | F9: 45778 | G9: 228000 | H9: ARS | I9: Trimestral | J9: 1 | K9: =IF(G9="","",G9*J9) -> 228000 | L9: =IF(K9="","",IF(H9="USD",K9*TC,K9)) | M9: 10 | N9: Activo
A10: 6 | B10: Inquilino 06 | C10: Local 06 | D10: 45444 | F10: 45809 | G10: 896 | H10: USD | I10: Trimestral | J10: 1 | K10: =IF(G10="","",G10*J10) -> 896 | L10: =IF(K10="","",IF(H10="USD",K10*TC,K10)) | M10: 5 | N10: Activo
A11: 7 | B11: Inquilino 07 | C11: Local 07 | D11: 45474 | F11: 45839 | G11: 645000 | H11: ARS | I11: Trimestral | J11: 1 | K11: =IF(G11="","",G11*J11) -> 645000 | L11: =IF(K11="","",IF(H11="USD",K11*TC,K11)) | M11: 1 | N11: Activo
A12: 8 | B12: Inquilino 08 | C12: Local 08 | D12: 45505 | F12: 45870 | G12: 289000 | H12: ARS | I12: Trimestral | J12: 1 | K12: =IF(G12="","",G12*J12) -> 289000 | L12: =IF(K12="","",IF(H12="USD",K12*TC,K12)) | M12: 5 | N12: Activo
A13: 9 | B13: Inquilino 09 | C13: Local 09 | D13: 45536 | F13: 45901 | G13: 224000 | H13: ARS | I13: Trimestral | J13: 1 | K13: =IF(G13="","",G13*J13) -> 224000 | L13: =IF(K13="","",IF(H13="USD",K13*TC,K13)) | M13: 10 | N13: Activo
A14: 10 | B14: Inquilino 10 | C14: Local 10 | D14: 45566 | F14: 45931 | G14: 394000 | H14: ARS | I14: Trimestral | J14: 1 | K14: =IF(G14="","",G14*J14) -> 394000 | L14: =IF(K14="","",IF(H14="USD",K14*TC,K14)) | M14: 5 | N14: Activo
A15: 11 | B15: Inquilino 11 | C15: Local 11 | D15: 45597 | F15: 45962 | G15: 546 | H15: USD | I15: Trimestral | J15: 1 | K15: =IF(G15="","",G15*J15) -> 546 | L15: =IF(K15="","",IF(H15="USD",K15*TC,K15)) | M15: 5 | N15: Activo
A16: 12 | B16: Inquilino 12 | C16: Local 12 | D16: 45627 | F16: 45992 | G16: 462000 | H16: ARS | I16: Trimestral | J16: 1 | K16: =IF(G16="","",G16*J16) -> 462000 | L16: =IF(K16="","",IF(H16="USD",K16*TC,K16)) | M16: 10 | N16: Activo
... A33: 29 | B33: Inquilino 29 | C33: Local 29 | D33: 45413 | F33: 45778 | G33: 370000 | H33: ARS | I33: Trimestral | J33: 1 | K33: =IF(G33="","",G33*J33) -> 370000 | L33: =IF(K33="","",IF(H33="USD",K33*TC,K33)) | M33: 5 | N33: Activo

Sheet Cobros
A1: REGISTRO DE COBROS DE ALQUILER
A2: Una fila por pago recibido. Elegí el ID del inquilino; el nombre y las conversiones se completan solos.
A4: Fecha cobro | B4: ID Inq. | C4: Inquilino | D4: Mes | E4: Período (texto) | F4: Monto | G4: Moneda | H4: Monto (ARS) | I4: Monto (USD) | J4: Medio de pago | K4: Estado | L4: Notas
A5: 46164.125 | C5: =IF($B5="","",IFERROR(VLOOKUP($B5,Inquilinos!$A:$B,2,0),"ID inexistente")) | D5: =IF($A5="","",MONTH($A5)) | F5: 500000 | G5: ARS | H5: =IF($F5="","",IF($G5="USD",$F5*TC,$F5)) | I5: =IF($F5="","",IF($G5="USD",$F5,$F5/TC)) | K5: Cobrado
A6: 46167.015 | D6: =IF($A6="","",MONTH($A6)) -> 5 | F6: 300000 | G6: ARS | H6: =IF($F6="","",IF($G6="USD",$F6*TC,$F6)) -> 300000 | I6: =IF($F6="","",IF($G6="USD",$F6,$F6/TC)) -> 261 | K6: Cobrado
C7: =IF($B7="","",IFERROR(VLOOKUP($B7,Inquilinos!$A:$B,2,0),"ID inexistente")) | D7: =IF($A7="","",MONTH($A7)) | H7: =IF($F7="","",IF($G7="USD",$F7*TC,$F7)) | I7: =IF($F7="","",IF($G7="USD",$F7,$F7/TC))
C8: =IF($B8="","",IFERROR(VLOOKUP($B8,Inquilinos!$A:$B,2,0),"ID inexistente")) | D8: =IF($A8="","",MONTH($A8)) | H8: =IF($F8="","",IF($G8="USD",$F8*TC,$F8)) | I8: =IF($F8="","",IF($G8="USD",$F8,$F8/TC))
C9: =IF($B9="","",IFERROR(VLOOKUP($B9,Inquilinos!$A:$B,2,0),"ID inexistente")) | D9: =IF($A9="","",MONTH($A9)) | H9: =IF($F9="","",IF($G9="USD",$F9*TC,$F9)) | I9: =IF($F9="","",IF($G9="USD",$F9,$F9/TC))
C10: =IF($B10="","",IFERROR(VLOOKUP($B10,Inquilinos!$A:$B,2,0),"ID inexistente")) | D10: =IF($A10="","",MONTH($A10)) | H10: =IF($F10="","",IF($G10="USD",$F10*TC,$F10)) | I10: =IF($F10="","",IF($G10="USD",$F10,$F10/TC))
C11: =IF($B11="","",IFERROR(VLOOKUP($B11,Inquilinos!$A:$B,2,0),"ID inexistente")) | D11: =IF($A11="","",MONTH($A11)) | H11: =IF($F11="","",IF($G11="USD",$F11*TC,$F11)) | I11: =IF($F11="","",IF($G11="USD",$F11,$F11/TC))
C12: =IF($B12="","",IFERROR(VLOOKUP($B12,Inquilinos!$A:$B,2,0),"ID inexistente")) | D12: =IF($A12="","",MONTH($A12)) | H12: =IF($F12="","",IF($G12="USD",$F12*TC,$F12)) | I12: =IF($F12="","",IF($G12="USD",$F12,$F12/TC))
C13: =IF($B13="","",IFERROR(VLOOKUP($B13,Inquilinos!$A:$B,2,0),"ID inexistente")) | D13: =IF($A13="","",MONTH($A13)) | H13: =IF($F13="","",IF($G13="USD",$F13*TC,$F13)) | I13: =IF($F13="","",IF($G13="USD",$F13,$F13/TC))
C14: =IF($B14="","",IFERROR(VLOOKUP($B14,Inquilinos!$A:$B,2,0),"ID inexistente")) | D14: =IF($A14="","",MONTH($A14)) | H14: =IF($F14="","",IF($G14="USD",$F14*TC,$F14)) | I14: =IF($F14="","",IF($G14="USD",$F14,$F14/TC))
C15: =IF($B15="","",IFERROR(VLOOKUP($B15,Inquilinos!$A:$B,2,0),"ID inexistente")) | D15: =IF($A15="","",MONTH($A15)) | H15: =IF($F15="","",IF($G15="USD",$F15*TC,$F15)) | I15: =IF($F15="","",IF($G15="USD",$F15,$F15/TC))
C16: =IF($B16="","",IFERROR(VLOOKUP($B16,Inquilinos!$A:$B,2,0),"ID inexistente")) | D16: =IF($A16="","",MONTH($A16)) | H16: =IF($F16="","",IF($G16="USD",$F16*TC,$F16)) | I16: =IF($F16="","",IF($G16="USD",$F16,$F16/TC))
C17: =IF($B17="","",IFERROR(VLOOKUP($B17,Inquilinos!$A:$B,2,0),"ID inexistente")) | D17: =IF($A17="","",MONTH($A17)) | H17: =IF($F17="","",IF($G17="USD",$F17*TC,$F17)) | I17: =IF($F17="","",IF($G17="USD",$F17,$F17/TC))
C18: =IF($B18="","",IFERROR(VLOOKUP($B18,Inquilinos!$A:$B,2,0),"ID inexistente")) | D18: =IF($A18="","",MONTH($A18)) | H18: =IF($F18="","",IF($G18="USD",$F18*TC,$F18)) | I18: =IF($F18="","",IF($G18="USD",$F18,$F18/TC))
... C404: =IF($B404="","",IFERROR(VLOOKUP($B404,Inquilinos!$A:$B,2,0),"ID inexistente")) | D404: =IF($A404="","",MONTH($A404)) | H404: =IF($F404="","",IF($G404="USD",$F404*TC,$F404)) | I404: =IF($F404="","",IF($G404="USD",$F404,$F404/TC))
E405: TOTAL cobrado | H405: =SUM(H5:H404) | I405: =SUM(I5:I404)

Sheet Movimientos
A1: MOVIMIENTOS DE LA FAMILIA — INGRESOS Y EGRESOS
A2: Registrá entradas y salidas de plata. Los alquileres ya se registran en 'Cobros'; acá van sueldos, gastos, impuestos, etc.
A4: Fecha | B4: Mes | C4: Tipo | D4: Miembro | E4: Categoría | F4: Descripción | G4: Monto | H4: Moneda | I4: Monto (ARS) | J4: Medio de pago | K4: Notas

Sheet Resumen Mensual
A1: RESUMEN MENSUAL (ARS)
A2: Todo automático: alquileres desde 'Cobros', otros ingresos y egresos desde 'Movimientos'.
A4: Mes | B4: N° | C4: Ingresos alquileres | D4: Otros ingresos | E4: Total ingresos | F4: Egresos | G4: Resultado neto | H4: Tasa de ahorro | I4: Acumulado
A5: Ene | B5: 1 | C5: =SUMIFS(Cobros!$H:$H,Cobros!$D:$D,$B5) | D5: =SUMIFS(Movimientos!$I:$I,Movimientos!$C:$C,"Ingreso",Movimientos!$B:$B,$B5) | E5: =C5+D5 | F5: =SUMIFS(Movimientos!$I:$I,Movimientos!$C:$C,"Egreso",Movimientos!$B:$B,$B5) | G5: =E5-F5 | H5: =IF(E5=0,"",G5/E5) | I5: =G5
A6: Feb | B6: 2 | C6: =SUMIFS(Cobros!$H:$H,Cobros!$D:$D,$B6) | D6: =SUMIFS(Movimientos!$I:$I,Movimientos!$C:$C,"Ingreso",Movimientos!$B:$B,$B6) | E6: =C6+D6 | F6: =SUMIFS(Movimientos!$I:$I,Movimientos!$C:$C,"Egreso",Movimientos!$B:$B,$B6) | G6: =E6-F6 | H6: =IF(E6=0,"",G6/E6) | I6: =I5+G6
A7: Mar | B7: 3 | C7: =SUMIFS(Cobros!$H:$H,Cobros!$D:$D,$B7) | D7: =SUMIFS(Movimientos!$I:$I,Movimientos!$C:$C,"Ingreso",Movimientos!$B:$B,$B7) | E7: =C7+D7 | F7: =SUMIFS(Movimientos!$I:$I,Movimientos!$C:$C,"Egreso",Movimientos!$B:$B,$B7) | G7: =E7-F7 | H7: =IF(E7=0,"",G7/E7) | I7: =I6+G7
A8: Abr | B8: 4 | C8: =SUMIFS(Cobros!$H:$H,Cobros!$D:$D,$B8) | D8: =SUMIFS(Movimientos!$I:$I,Movimientos!$C:$C,"Ingreso",Movimientos!$B:$B,$B8) | E8: =C8+D8 | F8: =SUMIFS(Movimientos!$I:$I,Movimientos!$C:$C,"Egreso",Movimientos!$B:$B,$B8) | G8: =E8-F8 | H8: =IF(E8=0,"",G8/E8) | I8: =I7+G8
A9: May | B9: 5 | C9: =SUMIFS(Cobros!$H:$H,Cobros!$D:$D,$B9) | D9: =SUMIFS(Movimientos!$I:$I,Movimientos!$C:$C,"Ingreso",Movimientos!$B:$B,$B9) | E9: =C9+D9 | F9: =SUMIFS(Movimientos!$I:$I,Movimientos!$C:$C,"Egreso",Movimientos!$B:$B,$B9) | G9: =E9-F9 | H9: =IF(E9=0,"",G9/E9) | I9: =I8+G9
A10: Jun | B10: 6 | C10: =SUMIFS(Cobros!$H:$H,Cobros!$D:$D,$B10) | D10: =SUMIFS(Movimientos!$I:$I,Movimientos!$C:$C,"Ingreso",Movimientos!$B:$B,$B10) | E10: =C10+D10 | F10: =SUMIFS(Movimientos!$I:$I,Movimientos!$C:$C,"Egreso",Movimientos!$B:$B,$B10) | G10: =E10-F10 | H10: =IF(E10=0,"",G10/E10) | I10: =I9+G10
A11: Jul | B11: 7 | C11: =SUMIFS(Cobros!$H:$H,Cobros!$D:$D,$B11) | D11: =SUMIFS(Movimientos!$I:$I,Movimientos!$C:$C,"Ingreso",Movimientos!$B:$B,$B11) | E11: =C11+D11 | F11: =SUMIFS(Movimientos!$I:$I,Movimientos!$C:$C,"Egreso",Movimientos!$B:$B,$B11) | G11: =E11-F11 | H11: =IF(E11=0,"",G11/E11) | I11: =I10+G11
A12: Ago | B12: 8 | C12: =SUMIFS(Cobros!$H:$H,Cobros!$D:$D,$B12) | D12: =SUMIFS(Movimientos!$I:$I,Movimientos!$C:$C,"Ingreso",Movimientos!$B:$B,$B12) | E12: =C12+D12 | F12: =SUMIFS(Movimientos!$I:$I,Movimientos!$C:$C,"Egreso",Movimientos!$B:$B,$B12) | G12: =E12-F12 | H12: =IF(E12=0,"",G12/E12) | I12: =I11+G12
A13: Sep | B13: 9 | C13: =SUMIFS(Cobros!$H:$H,Cobros!$D:$D,$B13) | D13: =SUMIFS(Movimientos!$I:$I,Movimientos!$C:$C,"Ingreso",Movimientos!$B:$B,$B13) | E13: =C13+D13 | F13: =SUMIFS(Movimientos!$I:$I,Movimientos!$C:$C,"Egreso",Movimientos!$B:$B,$B13) | G13: =E13-F13 | H13: =IF(E13=0,"",G13/E13) | I13: =I12+G13
A14: Oct | B14: 10 | C14: =SUMIFS(Cobros!$H:$H,Cobros!$D:$D,$B14) | D14: =SUMIFS(Movimientos!$I:$I,Movimientos!$C:$C,"Ingreso",Movimientos!$B:$B,$B14) | E14: =C14+D14 | F14: =SUMIFS(Movimientos!$I:$I,Movimientos!$C:$C,"Egreso",Movimientos!$B:$B,$B14) | G14: =E14-F14 | H14: =IF(E14=0,"",G14/E14) | I14: =I13+G14
A15: Nov | B15: 11 | C15: =SUMIFS(Cobros!$H:$H,Cobros!$D:$D,$B15) | D15: =SUMIFS(Movimientos!$I:$I,Movimientos!$C:$C,"Ingreso",Movimientos!$B:$B,$B15) | E15: =C15+D15 | F15: =SUMIFS(Movimientos!$I:$I,Movimientos!$C:$C,"Egreso",Movimientos!$B:$B,$B15) | G15: =E15-F15 | H15: =IF(E15=0,"",G15/E15) | I15: =I14+G15
A16: Dic | B16: 12 | C16: =SUMIFS(Cobros!$H:$H,Cobros!$D:$D,$B16) | D16: =SUMIFS(Movimientos!$I:$I,Movimientos!$C:$C,"Ingreso",Movimientos!$B:$B,$B16) | E16: =C16+D16 | F16: =SUMIFS(Movimientos!$I:$I,Movimientos!$C:$C,"Egreso",Movimientos!$B:$B,$B16) | G16: =E16-F16 | H16: =IF(E16=0,"",G16/E16) | I16: =I15+G16
A17: AÑO | C17: =SUM(C5:C16) | D17: =SUM(D5:D16) | E17: =SUM(E5:E16) | F17: =SUM(F5:F16) | G17: =SUM(G5:G16) | H17: =IF(E17=0,"",G17/E17)

Sheet Presupuesto
A1: PRESUPUESTO ANUAL POR CATEGORÍA (ARS)
A2: Cargá / ajustá el presupuesto mensual por categoría. El gasto real se calcula automáticamente desde Movimientos.
A4: Categoría | B4: Presup. mensual | C4: Presup. anual | D4: Gasto real (año) | E4: Desvío | F4: % usado
A5: Vivienda/Expensas | B5: 100000 | C5: =IF(B5="","",B5*12) | D5: =SUMIFS(Movimientos!$I:$I,Movimientos!$C:$C,"Egreso",Movimientos!$E:$E,$A5) -> 0 | E5: =IF(C5="","",C5-D5) | F5: =IF(OR(C5="",C5=0),"",D5/C5)
A6: Servicios (luz/gas/agua) | B6: 60000 | C6: =IF(B6="","",B6*12) | D6: =SUMIFS(Movimientos!$I:$I,Movimientos!$C:$C,"Egreso",Movimientos!$E:$E,$A6) -> 0 | E6: =IF(C6="","",C6-D6) | F6: =IF(OR(C6="",C6=0),"",D6/C6)
A7: Internet/Teléfono | B7: 30000 | C7: =IF(B7="","",B7*12) | D7: =SUMIFS(Movimientos!$I:$I,Movimientos!$C:$C,"Egreso",Movimientos!$E:$E,$A7) -> 0 | E7: =IF(C7="","",C7-D7) | F7: =IF(OR(C7="",C7=0),"",D7/C7)
A8: Supermercado/Comida | B8: 350000 | C8: =IF(B8="","",B8*12) | D8: =SUMIFS(Movimientos!$I:$I,Movimientos!$C:$C,"Egreso",Movimientos!$E:$E,$A8) -> 0 | E8: =IF(C8="","",C8-D8) | F8: =IF(OR(C8="",C8=0),"",D8/C8)
A9: Salud/Obra social | B9: 80000 | C9: =IF(B9="","",B9*12) | D9: =SUMIFS(Movimientos!$I:$I,Movimientos!$C:$C,"Egreso",Movimientos!$E:$E,$A9) -> 0 | E9: =IF(C9="","",C9-D9) | F9: =IF(OR(C9="",C9=0),"",D9/C9)
A10: Transporte/Auto | B10: 100000 | C10: =IF(B10="","",B10*12) | D10: =SUMIFS(Movimientos!$I:$I,Movimientos!$C:$C,"Egreso",Movimientos!$E:$E,$A10) -> 0 | E10: =IF(C10="","",C10-D10) | F10: =IF(OR(C10="",C10=0),"",D10/C10)
A11: Educación | B11: 50000 | C11: =IF(B11="","",B11*12) | D11: =SUMIFS(Movimientos!$I:$I,Movimientos!$C:$C,"Egreso",Movimientos!$E:$E,$A11) -> 0 | E11: =IF(C11="","",C11-D11) | F11: =IF(OR(C11="",C11=0),"",D11/C11)
A12: Impuestos (ABL/AFIP/Rentas) | B12: 80000 | C12: =IF(B12="","",B12*12) | D12: =SUMIFS(Movimientos!$I:$I,Movimientos!$C:$C,"Egreso",Movimientos!$E:$E,$A12) -> 0 | E12: =IF(C12="","",C12-D12) | F12: =IF(OR(C12="",C12=0),"",D12/C12)
A13: Mantenimiento locales | B13: 50000 | C13: =IF(B13="","",B13*12) | D13: =SUMIFS(Movimientos!$I:$I,Movimientos!$C:$C,"Egreso",Movimientos!$E:$E,$A13) -> 0 | E13: =IF(C13="","",C13-D13) | F13: =IF(OR(C13="",C13=0),"",D13/C13)
A14: Seguros | B14: 40000 | C14: =IF(B14="","",B14*12) | D14: =SUMIFS(Movimientos!$I:$I,Movimientos!$C:$C,"Egreso",Movimientos!$E:$E,$A14) -> 0 | E14: =IF(C14="","",C14-D14) | F14: =IF(OR(C14="",C14=0),"",D14/C14)
A15: Honorarios/Gestión | B15: 30000 | C15: =IF(B15="","",B15*12) | D15: =SUMIFS(Movimientos!$I:$I,Movimientos!$C:$C,"Egreso",Movimientos!$E:$E,$A15) -> 0 | E15: =IF(C15="","",C15-D15) | F15: =IF(OR(C15="",C15=0),"",D15/C15)
A16: Ocio/Viajes | B16: 80000 | C16: =IF(B16="","",B16*12) | D16: =SUMIFS(Movimientos!$I:$I,Movimientos!$C:$C,"Egreso",Movimientos!$E:$E,$A16) -> 0 | E16: =IF(C16="","",C16-D16) | F16: =IF(OR(C16="",C16=0),"",D16/C16)
... A19: Otros | B19: 30000 | C19: =IF(B19="","",B19*12) | D19: =SUMIFS(Movimientos!$I:$I,Movimientos!$C:$C,"Egreso",Movimientos!$E:$E,$A19) -> 0 | E19: =IF(C19="","",C19-D19) | F19: =IF(OR(C19="",C19=0),"",D19/C19)
A20: TOTAL | B20: =SUM(B5:B19) -> 0 | C20: =SUM(C5:C19) -> 0 | D20: =SUM(D5:D19) -> 0 | E20: =SUM(E5:E19) -> 0 | F20: =IF(OR(C20="",C20=0),"",D20/C20)

Sheet Indicadores
A1: INDICADORES FINANCIEROS
A2: Panel para tomar decisiones. Todo se calcula desde las demás hojas.
B4: Resultado del año | F4: Egresos por miembro
B5: Indicador | C5: Valor | D5: Lectura / comentario | F5: Miembro | G5: Mes actual | H5: Año
B6: Ingresos totales (año) | C6: ='Resumen Mensual'!$E$17 | D6: Alquileres + otros ingresos. | F6: José | G6: =SUMIFS(Movimientos!$I:$I,Movimientos!$C:$C,"Egreso",Movimientos!$D:$D,"José",Movimientos!$B:$B,MONTH(TODAY())) -> 0 | H6: =SUMIFS(Movimientos!$I:$I,Movimientos!$C:$C,"Egreso",Movimientos!$D:$D,"José") -> 0
B7: Egresos totales (año) | C7: ='Resumen Mensual'!$F$17 | D7: Todos los gastos cargados. | F7: Clara | G7: =SUMIFS(Movimientos!$I:$I,Movimientos!$C:$C,"Egreso",Movimientos!$D:$D,"Clara",Movimientos!$B:$B,MONTH(TODAY())) -> 0 | H7: =SUMIFS(Movimientos!$I:$I,Movimientos!$C:$C,"Egreso",Movimientos!$D:$D,"Clara") -> 0
B8: Resultado neto (año) | C8: ='Resumen Mensual'!$G$17 | D8: Lo que la familia ahorró/consumió. | F8: Laura | G8: =SUMIFS(Movimientos!$I:$I,Movimientos!$C:$C,"Egreso",Movimientos!$D:$D,"Laura",Movimientos!$B:$B,MONTH(TODAY())) -> 0 | H8: =SUMIFS(Movimientos!$I:$I,Movimientos!$C:$C,"Egreso",Movimientos!$D:$D,"Laura") -> 0
B9: Tasa de ahorro anual | C9: =IF('Resumen Mensual'!$E$17=0,"",'Resumen Mensual'!$G$17/'Resumen Mensual'!$E$17) | D9: Sano > 20%. Cuanto más alto, mejor. | F9: Familia | G9: =SUMIFS(Movimientos!$I:$I,Movimientos!$C:$C,"Egreso",Movimientos!$D:$D,"Familia",Movimientos!$B:$B,MONTH(TODAY())) -> 0 | H9: =SUMIFS(Movimientos!$I:$I,Movimientos!$C:$C,"Egreso",Movimientos!$D:$D,"Familia") -> 0
B10: Ratio egresos / ingresos | C10: =IF('Resumen Mensual'!$E$17=0,"",'Resumen Mensual'!$F$17/'Resumen Mensual'!$E$17) | D10: Debajo de 80% deja margen de ahorro. | F10: TOTAL | G10: =SUM(G6:G9) -> 0 | H10: =SUM(H6:H9) -> 0
B12: Promedios mensuales
B13: Indicador | C13: Valor | D13: Lectura / comentario | F13: Egresos por categoría (año)
B14: Ingreso promedio mensual | C14: =AVERAGE('Resumen Mensual'!E5:E16) | D14: Promedio de los 12 meses. | F14: Categoría | G14: Egresos | H14: % del total
B15: Egreso promedio mensual | C15: =AVERAGE('Resumen Mensual'!F5:F16) | D15: Promedio de los 12 meses. | F15: Vivienda/Expensas | G15: =Presupuesto!D5 | H15: =IF('Resumen Mensual'!$F$17=0,"",G15/'Resumen Mensual'!$F$17)
B16: Ahorro promedio mensual | C16: =AVERAGE('Resumen Mensual'!G5:G16) | D16: Resultado neto medio. | F16: Servicios (luz/gas/agua) | G16: =Presupuesto!D6 | H16: =IF('Resumen Mensual'!$F$17=0,"",G16/'Resumen Mensual'!$F$17)
F17: Internet/Teléfono | G17: =Presupuesto!D7 | H17: =IF('Resumen Mensual'!$F$17=0,"",G17/'Resumen Mensual'!$F$17)
B18: Alquileres / cobranza | F18: Supermercado/Comida | G18: =Presupuesto!D8 | H18: =IF('Resumen Mensual'!$F$17=0,"",G18/'Resumen Mensual'!$F$17)
B19: Indicador | C19: Valor | D19: Lectura / comentario | F19: Salud/Obra social | G19: =Presupuesto!D9 | H19: =IF('Resumen Mensual'!$F$17=0,"",G19/'Resumen Mensual'!$F$17)
B20: Alquiler esperado (año) | C20: ='Tablero Inquilinos'!$Q$34 | D20: Ya reajustado por inflación INDEC. | F20: Transporte/Auto | G20: =Presupuesto!D10 | H20: =IF('Resumen Mensual'!$F$17=0,"",G20/'Resumen Mensual'!$F$17)
B21: Alquiler cobrado (año) | C21: ='Tablero Inquilinos'!$O$34 | D21: Total efectivamente cobrado. | F21: Educación | G21: =Presupuesto!D11 | H21: =IF('Resumen Mensual'!$F$17=0,"",G21/'Resumen Mensual'!$F$17)
B22: Tasa de cobranza | C22: =IF('Tablero Inquilinos'!$Q$34=0,"",'Tablero Inquilinos'!$O$34/'Tablero Inquilinos'!$Q$34) | D22: Objetivo: cerca del 100%. | F22: Impuestos (ABL/AFIP/Rentas) | G22: =Presupuesto!D12 | H22: =IF('Resumen Mensual'!$F$17=0,"",G22/'Resumen Mensual'!$F$17)
B23: Morosidad | C23: =IF('Tablero Inquilinos'!$Q$34=0,"",1-'Tablero Inquilinos'!$O$34/'Tablero Inquilinos'!$Q$34) | D23: Lo que falta cobrar. Cuanto más bajo, mejor. | F23: Mantenimiento locales | G23: =Presupuesto!D13 | H23: =IF('Resumen Mensual'!$F$17=0,"",G23/'Resumen Mensual'!$F$17)
B24: Ingreso medio por local (mensual) | C24: =IF(COUNT(Inquilinos!P5:P33)=0,"",AVERAGE(Inquilinos!P5:P33)) | D24: Renta media reajustada por inquilino. | F24: Seguros | G24: =Presupuesto!D14 | H24: =IF('Resumen Mensual'!$F$17=0,"",G24/'Resumen Mensual'!$F$17)
B25: Concentración: mayor inquilino | C25: =IF('Tablero Inquilinos'!$Q$34=0,"",MAX('Tablero Inquilinos'!Q5:Q33)/'Tablero Inquilinos'!$Q$34) | D25: Si es alto, dependés mucho de un local. | F25: Honorarios/Gestión | G25: =Presupuesto!D15 | H25: =IF('Resumen Mensual'!$F$17=0,"",G25/'Resumen Mensual'!$F$17)
F26: Ocio/Viajes | G26: =Presupuesto!D16 | H26: =IF('Resumen Mensual'!$F$17=0,"",G26/'Resumen Mensual'!$F$17)
B27: Liquidez y respaldo | F27: Indumentaria | G27: =Presupuesto!D17 | H27: =IF('Resumen Mensual'!$F$17=0,"",G27/'Resumen Mensual'!$F$17)
B28: Indicador | C28: Valor | D28: Lectura / comentario | F28: Ahorro/Inversión | G28: =Presupuesto!D18 | H28: =IF('Resumen Mensual'!$F$17=0,"",G28/'Resumen Mensual'!$F$17)
B29: Saldo disponible hoy | C29: =SaldoHoy | D29: Cargalo en 'Parámetros'. | F29: Otros | G29: =Presupuesto!D19 | H29: =IF('Resumen Mensual'!$F$17=0,"",G29/'Resumen Mensual'!$F$17)
B30: Fondo de emergencia (meses cubiertos) | C30: =IF(AVERAGE('Resumen Mensual'!F5:F16)=0,"",SaldoHoy/AVERAGE('Resumen Mensual'!F5:F16)) | D30: Meses que aguantás sin ingresos.
B31: Objetivo fondo de emergencia (ARS) | C31: =FondoObj*AVERAGE('Resumen Mensual'!F5:F16) | D31: Meses objetivo × egreso medio.
B32: Brecha vs objetivo de fondo | C32: =FondoObj*AVERAGE('Resumen Mensual'!F5:F16)-SaldoHoy | D32: Lo que falta ahorrar para el colchón.
